pydocify/__init__.py
pydocify/core.py
pydocify-0.2.1.dist-info/LICENSE
pydocify-0.2.1.dist-info/METADATA
pydocify-0.2.1.dist-info/WHEEL
pydocify-0.2.1.dist-info/top_level.txt
pydocify-0.2.1.dist-info/RECORD
