Metadata-Version: 2.1
Name: pydocify
Version: 0.2.1
Summary: pydocify: An LLM-based library that effortlessly auto-generates docstrings for your Python scripts and modules, enhancing code readability with ease.
Home-page: https://github.com/rahulbhoyar1995/pydocify.git
Author: Rahul Bhoyar
Author-email: rahulbhoyaroffice@gmail.com
License: UNKNOWN
Platform: UNKNOWN
Classifier: Programming Language :: Python :: 3
Classifier: License :: OSI Approved :: MIT License
Classifier: Operating System :: OS Independent
Requires-Python: >=3.6
License-File: LICENSE
Requires-Dist: langchain-core
Requires-Dist: langchain-openai
Requires-Dist: python-dotenv
Requires-Dist: tiktoken
Requires-Dist: tqdm
Requires-Dist: urllib3 (==2.2.3)
